subnet_info/__init__.py
subnet_info/helpers.py
subnet_info/state.py
subnet_info/subnet_info.py
subnetinfo-1.1.dist-info/LICENSE
subnetinfo-1.1.dist-info/METADATA
subnetinfo-1.1.dist-info/WHEEL
subnetinfo-1.1.dist-info/top_level.txt
subnetinfo-1.1.dist-info/RECORD
