Metadata-Version: 2.1
Name: subnetinfo
Version: 1.1
Summary: Get information about chosen subnet
Home-page: https://github.com/kacperstyslo/subnet_info
Author: Kacper Styslo
Author-email: kacper.styslo@gmail.com
License: UNKNOWN
Platform: UNKNOWN
Classifier: Intended Audience :: Developers
Classifier: Programming Language :: Python :: 3
Classifier: License :: OSI Approved :: MIT License
Classifier: Development Status :: 5 - Production/Stable
Classifier: Operating System :: POSIX :: Linux
Classifier: Operating System :: Microsoft :: Windows :: Windows 10
Requires-Python: >=3.6
License-File: LICENSE
Requires-Dist: requests (==2.26.0)
